mcp_tip/__init__.py
mcp_tip/server.py
tests/__init__.py
tests/test_ip_only.py
tests/test_server.py
mcp_tip-0.2.0.dist-info/METADATA
mcp_tip-0.2.0.dist-info/WHEEL
mcp_tip-0.2.0.dist-info/entry_points.txt
mcp_tip-0.2.0.dist-info/top_level.txt
mcp_tip-0.2.0.dist-info/RECORD
