Metadata-Version: 2.4
Name: mcp-tip
Version: 0.2.0
Summary: ThreatBook 威胁情报查询 MCP 工具
Author: FBX
Author-email: FBX <your_email@example.com>
Classifier: Programming Language :: Python :: 3
Classifier: Operating System :: OS Independent
Requires-Python: >=3.10
Requires-Dist: requests>=2.31
Requires-Dist: fastmcp>=0.1.0
Requires-Dist: pydantic>=2.0.0
Dynamic: author
Dynamic: requires-python
